<mockup version="5.3" minAllowVersion="5.3" ID="2CD30FA5-3402-4C33-BB08-7976750507E2" platform="MtMobile" defaultW="375" defaultH="667" measureW="375" measureH="667" screenOrientation="MoPortrait" mobileScreenScale="1.77777779102325">
  <controls controlCount="10">
    <control controlID="6704C4AE-2D31-4542-AF47-AC0EE471FB62" controlTypeID="Image" x="0" y="0" w="375" h="669" zOrder="0">
      <URL>1F13E35966C60726EEE863DB4AB96058.jpg</URL>
    </control>
    <control controlID="CC5617C3-ED93-40CB-9448-B27B2E583FE8" controlTypeID="Image" x="0" y="337" w="375" h="332" zOrder="1">
      <URL>D667382F0A6643D868E8BBFEC04FB58C.png</URL>
    </control>
    <control controlID="C2A845ED-05ED-4578-B1C6-19D1DEBF6040" controlTypeID="TextArea" x="181" y="348" w="240" h="218" zOrder="2">
      <font family="%E5%8D%8E%E6%96%87%E8%A1%8C%E6%A5%B7" displayName="%E5%8D%8E%E6%96%87%E8%A1%8C%E6%A5%B7" postScript="" weightStyle="Regular" weight="400" isBold="False" isItalic="False" useDefaultFontFamily="False"/>
      <text>%E4%BE%8D%0D%0A%E4%B9%A6</text>
      <textSize>72</textSize>
      <textAlign>HaCenter</textAlign>
      <selectedIndex>-1</selectedIndex>
    </control>
    <control controlID="831D548B-E5AD-4F9A-AD38-D33A298D3C7A" controlTypeID="Button" x="28" y="279" w="120" h="48" zOrder="3">
      <color>4288647018</color>
      <borderColor>4290911259</borderColor>
      <borderVisible>False</borderVisible>
      <links eventType="AtClick" animate="AmNone" animateAutoDelay="0" animateDuration="500">
        <link targetPageID="27323A06-C121-43F0-BAE9-6D9FC23153E7" linkType="ltPageLink" isApplyIncludePage="False" title="%E8%B4%BE%E6%8E%A2%E6%98%A5">
          <area shape="0" alt="" ID="{3A7FF8FB-93FA-495A-9A48-30A5717ACC6F}" coords="(0,0,120,48)"/>
        </link>
      </links>
      <font family="%E6%96%B9%E6%AD%A3%E5%A7%9A%E4%BD%93" displayName="%E6%96%B9%E6%AD%A3%E5%A7%9A%E4%BD%93" postScript="" weightStyle="Regular" weight="400" isBold="False" isItalic="False" useDefaultFontFamily="False"/>
      <text>%E4%B8%BB</text>
      <textColor>4294967295</textColor>
      <textSize>24</textSize>
      <lineSpacing>0</lineSpacing>
      <selectedIndex>-1</selectedIndex>
      <radius>100</radius>
      <radiusIsPercent>True</radiusIsPercent>
    </control>
    <control controlID="84409718-5C70-4858-82BC-100FB4DE7694" controlTypeID="Top ActionBar" x="0" y="0" w="375" h="35" zOrder="4">
      <color>4290091377</color>
      <opacity>0.699999988079071</opacity>
      <links eventType="AtClick" animate="AmNone" animateAutoDelay="0" animateDuration="500">
        <link targetPageID="A664BD04-CC58-469F-A0B5-6C37A72C394C" linkType="ltPageLink" isApplyIncludePage="False" title="%E9%A6%96%E9%A1%B5">
          <area shape="0" alt="" ID="{0D497F1F-A182-4D9E-BEA7-3C1498DD9E34}" coords="(4.5,0.5,39.5,35.5)"/>
        </link>
        <link targetPageID="" linkType="ltPageLink" isApplyIncludePage="False" title="%E8%8F%9C%E5%8D%95">
          <area shape="0" alt="" ID="{119B12B8-5D0D-4329-B10D-ECF9BF3F14E3}" coords="(330.5,0.5,365.5,35.5)"/>
        </link>
      </links>
      <interactiveData>
        <entry title="%E8%BF%94%E5%9B%9E">
          <area shape="0" alt="" ID="{2A0905C2-6913-4498-AD15-7068FCA6B45E}" coords="(4.5,0.5,39.5,35.5)"/>
          <events title=""/>
        </entry>
        <entry title="%E8%8F%9C%E5%8D%95">
          <area shape="0" alt="" ID="{23B8D8FC-098E-470E-96BB-F10C30C2586B}" coords="(330.5,0.5,365.5,35.5)"/>
          <events title="">
            <event eventType="atClick" isChecked="True">
              <behaviour title="" isChecked="True" isWait="False" isLoop="False" execMode="emParallel">
                <target targetID="ADB8417F-ABA4-424E-9076-830EAECD3C48" isChecked="True" isAutoRecovery="False" isLoop="False" execMode="emSequence">
                  <command name="Popup State Change" isChecked="True" descrition="">
                    <param name="AniInterpolation" value="0" varType="3" description=""/>
                    <param name="AniDuration" value="200" varType="3" description=""/>
                    <param name="AniAutoReverse" value="False" varType="11" description=""/>
                    <param name="AniLoop" value="False" varType="11" description=""/>
                    <param name="AniInterpolationTypeOut" value="False" varType="11" description=""/>
                    <param name="Delay" value="0" varType="3" description=""/>
                    <param name="Value" value="2" varType="3" description=""/>
                    <param name="AniType" value="0" varType="3" description=""/>
                  </command>
                </target>
              </behaviour>
            </event>
          </events>
        </entry>
      </interactiveData>
      <font family="Segoe+UI" displayName="Segoe+UI" postScript="" weightStyle="Regular" weight="400" isBold="False" isItalic="False" useDefaultFontFamily="False"/>
      <textSize>14</textSize>
      <lineSpacing>0</lineSpacing>
      <useDefaultTextSize>False</useDefaultTextSize>
      <iconColor>4281475860</iconColor>
    </control>
    <control controlID="ADB8417F-ABA4-424E-9076-830EAECD3C48" controlTypeID="PopupMenu" x="450" y="124" w="46" h="46" zOrder="5">
      <caption>%E8%BF%94%E5%9B%9E%E8%8F%9C%E5%8D%95</caption>
      <groupChildrenDescriptors>
        <control controlID="063B9DD2-E9CE-48AC-941B-C6DB843351DE" controlTypeID="Panel" x="0" y="0" w="375" h="667" zOrder="0">
          <locked>True</locked>
          <color>1879048192</color>
          <borderVisible>False</borderVisible>
          <canMove>False</canMove>
          <alias>background</alias>
          <groupChildrenDescriptors>
            <control controlID="3CA01D29-4967-46FC-9748-328C6C1991D8" controlTypeID="Border" x="0" y="0" w="375" h="667" zOrder="0">
              <borderVisible>False</borderVisible>
              <alias>borderLayer</alias>
            </control>
          </groupChildrenDescriptors>
          <thinkness>1</thinkness>
        </control>
        <control controlID="2ADFEF8A-29A4-4FA5-94BA-22B1C2BF6CDA" controlTypeID="PopupPanelContent" x="195" y="0" w="180" h="97" zOrder="1">
          <borderVisible>True</borderVisible>
          <alias>content</alias>
          <groupChildrenDescriptors>
            <control controlID="68643794-590F-4C4E-BDEB-5FDBE8A421BD" controlTypeID="List" x="0" y="0" w="180" h="97" zOrder="0">
              <color>4294108099</color>
              <alias>menu</alias>
              <links eventType="AtClick" animate="AmNone" animateAutoDelay="0" animateDuration="500">
                <link targetPageID="3BAD539F-A9AE-4DD9-B6F0-6540EB41638E" linkType="ltPageLink" isApplyIncludePage="False" title="%E8%BF%94%E5%9B%9E%E5%85%A8%E7%9B%AE%E5%BD%95">
                  <area shape="0" alt="" ID="{79C91BF8-088A-4FCF-BF48-2F938380FD52}" coords="(1,1,179,49)"/>
                </link>
                <link targetPageID="85871498-5675-4303-8528-7E5AC97CF3F8" linkType="ltPageLink" isApplyIncludePage="False" title="%E8%BF%94%E5%9B%9E%E4%B8%BB%E8%A6%81%E4%BA%BA%E7%89%A9%E7%B4%A2%E5%BC%95">
                  <area shape="0" alt="" ID="{E14DF13C-A4BE-4D9D-A7A8-DDE95E9B89BA}" coords="(1,49,179,97)"/>
                </link>
              </links>
              <font family="%E4%BB%BF%E5%AE%8B" displayName="%E4%BB%BF%E5%AE%8B" postScript="" weightStyle="Regular" weight="400" isBold="False" isItalic="False" useDefaultFontFamily="False"/>
              <text>%E8%BF%94%E5%9B%9E%E5%85%A8%E7%9B%AE%E5%BD%95%0D%0A%E8%BF%94%E5%9B%9E%E4%B8%BB%E8%A6%81%E4%BA%BA%E7%89%A9%E7%B4%A2%E5%BC%95</text>
              <textSize>20</textSize>
              <textAlign>HaCenter</textAlign>
              <lineSpacing>0</lineSpacing>
              <selectedColor>4290091377</selectedColor>
              <itemHeight>48</itemHeight>
              <showSeparator>True</showSeparator>
              <selectedTextColor>4294108099</selectedTextColor>
            </control>
          </groupChildrenDescriptors>
        </control>
      </groupChildrenDescriptors>
    </control>
  </controls>
  <param>
    <backgroundColor>4294967295</backgroundColor>
    <fontSize>0</fontSize>
    <fontFamily/>
    <guideLines/>
  </param>
</mockup>